tkinter_bounce_game/__init__.py
tkinter_bounce_game/__main__.py
tkinter_bounce_game/context.py
tkinter_bounce_game/py.typed
tkinter_bounce_game/sprite.py
tkinter_bounce_game-0.2.1.dist-info/LICENSE
tkinter_bounce_game-0.2.1.dist-info/METADATA
tkinter_bounce_game-0.2.1.dist-info/WHEEL
tkinter_bounce_game-0.2.1.dist-info/RECORD
