Metadata-Version: 2.1
Name: tkinter-bounce-game
Version: 0.2.1
Summary: Simple bounce game with Python and tkinter
Home-page: https://github.com/4513ECHO/tkinter-bounce-game
License: MIT
Author: 4513ECHO
Author-email: mail@4513echo.dev
Requires-Python: >=3.10,<4.0
Classifier: License :: OSI Approved :: MIT License
Classifier: Programming Language :: Python
Classifier: Programming Language :: Python :: 3
Classifier: Programming Language :: Python :: 3.10
Classifier: Programming Language :: Python :: 3.11
Classifier: Programming Language :: Python :: 3
Classifier: Programming Language :: Python :: 3 :: Only
Classifier: Programming Language :: Python :: 3.10
Classifier: Programming Language :: Python :: Implementation :: CPython
Classifier: Topic :: Games/Entertainment
Classifier: Typing :: Typed
Project-URL: Repository, https://github.com/4513ECHO/tkinter-bounce-game
